Metadata-Version: 1.0
Name: GausBi-Distributions
Version: 1.1
Summary: Gaussian and Binomial Distributions
Home-page: UNKNOWN
Author: CM
Author-email: UNKNOWN
License: UNKNOWN
Platform: UNKNOWN
